volt/__init__.py
volt/app.py
volt/app_test.py
volt/asgi.py
volt/cli.py
volt/components.py
volt/components.py.j2
volt/config.py
volt/generator.py
volt/generator_test.py
volt/http.py
volt/lifespan_test.py
volt/log.py
volt/middleware.py
volt/trie.py
volt/trie_test.py
volt_framework-0.2.2.dist-info/licenses/LICENSE
volt_framework-0.2.2.dist-info/METADATA
volt_framework-0.2.2.dist-info/WHEEL
volt_framework-0.2.2.dist-info/entry_points.txt
volt_framework-0.2.2.dist-info/top_level.txt
volt_framework-0.2.2.dist-info/RECORD
