Metadata-Version: 2.4
Name: volt-framework
Version: 0.2.2
Summary: A lightning-fast, opinionated web framework with a high-performance Zig substrate
Author-email: Nick Henderson <nick@trkl.dev>
License-Expression: MIT
Project-URL: Homepage, https://volt.trkl.dev
Project-URL: Issues, https://github.com/trkl-dev/volt/issues
Project-URL: Source, https://github.com/trkl-dev/volt
Keywords: web,framework,http,async,performance,zig
Classifier: Development Status :: 3 - Alpha
Classifier: Intended Audience :: Developers
Classifier: Operating System :: POSIX :: Linux
Classifier: Operating System :: MacOS
Classifier: Programming Language :: Python :: 3
Classifier: Programming Language :: Python :: 3.12
Classifier: Programming Language :: Python :: 3.13
Classifier: Topic :: Internet :: WWW/HTTP :: HTTP Servers
Classifier: Topic :: Software Development :: Libraries :: Application Frameworks
Requires-Python: >=3.12
License-File: LICENSE
Requires-Dist: jinja2
Provides-Extra: dev
Requires-Dist: pywatchman; extra == "dev"
Provides-Extra: maintainer
Requires-Dist: pytest; extra == "maintainer"
Requires-Dist: requests; extra == "maintainer"
Requires-Dist: uvicorn; extra == "maintainer"
Provides-Extra: build
Requires-Dist: setuptools; extra == "build"
Requires-Dist: setuptools_scm; extra == "build"
Requires-Dist: build; extra == "build"
Requires-Dist: wheel; extra == "build"
Requires-Dist: twine; extra == "build"
Dynamic: license-file
